rest_jwt_permission/__init__.py
rest_jwt_permission/apps.py
rest_jwt_permission/handlers.py
rest_jwt_permission/models.py
rest_jwt_permission/permissions.py
rest_jwt_permission/settings.py
rest_jwt_permission/utils.py
rest_jwt_permission/management/__init__.py
rest_jwt_permission/management/commands/__init__.py
rest_jwt_permission/management/commands/show_roles.py
rest_jwt_permission/providers/__init__.py
rest_jwt_permission/providers/admin.py
rest_jwt_permission/providers/api_endpoint.py
rest_jwt_permission/providers/base.py
rest_jwt_permission/providers/utils.py
rest_jwt_permission/scopes/__init__.py
rest_jwt_permission/scopes/api.py
rest_jwt_permission/scopes/base.py
rest_jwt_permission/scopes/simple.py
rest_jwt_permission/scopes/utils.py
rest_jwt_permission_tests/__init__.py
rest_jwt_permission_tests/conftest.py
rest_jwt_permission_tests/factories.py
rest_jwt_permission_tests/settings.py
rest_jwt_permission_tests/test_handlers.py
rest_jwt_permission_tests/test_permissions.py
rest_jwt_permission_tests/test_scopes.py
rest_jwt_permission_tests/test_utils.py
rest_jwt_permission_tests/urls.py
rest_jwt_permission_tests/providers/__init__.py
rest_jwt_permission_tests/providers/test_admin_provider.py
rest_jwt_permission_tests/providers/test_api_endpoint_provider.py
rest_jwt_permission_tests/providers/test_providers.py
django3_rest_jwt_permission-1.0.2.dist-info/LICENSE
django3_rest_jwt_permission-1.0.2.dist-info/METADATA
django3_rest_jwt_permission-1.0.2.dist-info/WHEEL
django3_rest_jwt_permission-1.0.2.dist-info/top_level.txt
django3_rest_jwt_permission-1.0.2.dist-info/RECORD
