Metadata-Version: 2.1
Name: django3-rest-jwt-permission
Version: 1.0.2
Summary: Django3 Rest Framework JWT Permissions
Home-page: https://github.com/tend/rest-jwt-permission
Author: Rati Matchavariani
Author-email: rati.matchavariani@hellotend.com
License: MIT
Classifier: Programming Language :: Python
Classifier: Programming Language :: Python :: 3.8
Classifier: Environment :: Web Environment
Classifier: Topic :: Internet :: WWW/HTTP
Classifier: Intended Audience :: Developers
License-File: LICENSE
